test/dff.v
module dff(input d,clk,rst, output reg out);

always @(posedge clk or rst)
begin
    if (rst==0)
        out<=0;
    else
        if (d==1)
            out<=1;
        else
            out<=0;
end 

endmodule

test/dff_testbench.v
`timescale 1ns/1ps
module dff_testbench;

reg d,clk,rst;
wire out;

dff DUT(d,clk,rst,out);

initial begin
d<=0;
clk<=0;
rst<=0;
#200 $finish;

end

always #10 clk<=~clk;
always #100 rst<=~rst;


always begin
#20 d<=0;
#20 d<=1;


end

initial begin
    $dumpfile("dff.vcd");
    $dumpvars;
    $monitor("%g clk= %b  d=%b  rst = %b out=%b",$time,clk,d,rst,out);
end

endmodule

test/dff.vcd
$date
	Fri Apr 08 14:31:45 2022
$end
$version
	Icarus Verilog
$end
$timescale
	1ps
$end
$scope module dff_testbench $end
$var wire 1 ! out $end
$var reg 1 " clk $end
$var reg 1 # d $end
$var reg 1 $ rst $end
$scope module DUT $end
$var wire 1 " clk $end
$var wire 1 # d $end
$var wire 1 $ rst $end
$var reg 1 ! out $end
$upscope $end
$upscope $end
$enddefinitions $end
#0
$dumpvars
0$
0#
0"
0!
$end
#10000
1"
#20000
0"
#30000
1"
#40000
0"
1#
#50000
1"
#60000
0"
0#
#70000
1"
#80000
0"
1#
#90000
1"
#100000
0"
0#
1$
#110000
1"
#120000
0"
1#
#130000
1!
1"
#140000
0"
0#
#150000
0!
1"
#160000
0"
1#
#170000
1!
1"
#180000
0"
0#
#190000
0!
1"
#200000
0"
1#
0$
