Assignment_1/2a/2x1_mux.v
module mux2x1(input s0,a,b,output out);
assign out= s0? b:a;
endmodule

Assignment_1/2a/2x1_mux_tb.v
`timescale  1ns/10ps

module mux_tb;

reg s0,a,b;
wire out;

mux2x1 DUT(s0,a,b,out);

initial
begin
       


   #10 s0=0;a=0;b=0; 
   #10 s0=0;a=0;b=1; 
   #10 s0=0;a=1;b=0; 
   #10 s0=0;a=1;b=1; 
   #10 s0=1;a=0;b=0; 
   #10 s0=1;a=0;b=1; 
   #10 s0=1;a=1;b=0; 
   #10 s0=1;a=1;b=1; 

end

initial begin
   	$monitor("%g s0=%b a=%b b=%b, out=%b ",$time,s0,a,b,out);

      $dumpfile("q_2a.vcd");
      $dumpvars;
end
endmodule

Assignment_1/2a/q_2a.vcd
$date
	Sun Feb 20 11:13:56 2022
$end
$version
	Icarus Verilog
$end
$timescale
	10ps
$end
$scope module mux_tb $end
$var wire 1 ! out $end
$var reg 1 " a $end
$var reg 1 # b $end
$var reg 1 $ s0 $end
$scope module DUT $end
$var wire 1 " a $end
$var wire 1 # b $end
$var wire 1 $ s0 $end
$var wire 1 ! out $end
$upscope $end
$upscope $end
$enddefinitions $end
#0
$dumpvars
x$
x#
x"
x!
$end
#1000
0!
0#
0"
0$
#2000
1#
#3000
1!
0#
1"
#4000
1#
#5000
0!
0#
0"
1$
#6000
1!
1#
#7000
0!
0#
1"
#8000
1!
1#
