Assignment_1/2b/4x1_mux.v
module mux4x1(input s0,s1,a,b,c,d,output out);
assign out= s1? (s0?d:b): (s0?c:a);
endmodule

Assignment_1/2b/4x1_mux_tb.v
`timescale  1ns/10ps

module mux_tb;

reg s0,s1,a,b,c,d;
wire out;

mux4x1 DUT(s0,s1,a,b,c,d,out);


initial begin
    s0=1'b0;    
    s1=1'b0;    
    a=1'b0;    
    b=1'b0;        
    c=1'b0;    
    d=1'b0;    
    #1000 $finish;
end

always #400 s0= ~s0;
always #200 s1= ~s1;
always #100 a= ~a;
always #50   b= ~b;
always #25 c= ~c;
always #12.5 d= ~d;

initial begin
   	$monitor("%g Output=%b s0=%b s1=%b a=%b b=%b c=%b d=%b",$time,out,s0,s1,a,b,c,d);

    $dumpfile("q_2b.vcd");
    $dumpvars;
end
endmodule

Assignment_1/2b/q_2b.vcd
$date
	Sun Feb 20 16:04:56 2022
$end
$version
	Icarus Verilog
$end
$timescale
	10ps
$end
$scope module mux_tb $end
$var wire 1 ! out $end
$var reg 1 " a $end
$var reg 1 # b $end
$var reg 1 $ c $end
$var reg 1 % d $end
$var reg 1 & s0 $end
$var reg 1 ' s1 $end
$scope module DUT $end
$var wire 1 " a $end
$var wire 1 # b $end
$var wire 1 $ c $end
$var wire 1 % d $end
$var wire 1 & s0 $end
$var wire 1 ' s1 $end
$var wire 1 ! out $end
$upscope $end
$upscope $end
$enddefinitions $end
#0
$dumpvars
0'
0&
0%
0$
0#
0"
0!
$end
#1250
1%
#2500
0%
1$
#3750
1%
#5000
0%
0$
1#
#6250
1%
#7500
0%
1$
#8750
1%
#10000
1!
0%
0$
0#
1"
#11250
1%
#12500
0%
1$
#13750
1%
#15000
0%
0$
1#
#16250
1%
#17500
0%
1$
#18750
1%
#20000
0!
0%
0$
0#
0"
1'
#21250
1%
#22500
0%
1$
#23750
1%
#25000
1!
0%
0$
1#
#26250
1%
#27500
0%
1$
#28750
1%
#30000
0!
0%
0$
0#
1"
#31250
1%
#32500
0%
1$
#33750
1%
#35000
1!
0%
0$
1#
#36250
1%
#37500
0%
1$
#38750
1%
#40000
0!
0%
0$
0#
0"
0'
1&
#41250
1%
#42500
1!
0%
1$
#43750
1%
#45000
0!
0%
0$
1#
#46250
1%
#47500
1!
0%
1$
#48750
1%
#50000
0!
0%
0$
0#
1"
#51250
1%
#52500
1!
0%
1$
#53750
1%
#55000
0!
0%
0$
1#
#56250
1%
#57500
1!
0%
1$
#58750
1%
#60000
0!
0%
0$
0#
0"
1'
#61250
1!
1%
#62500
0!
0%
1$
#63750
1!
1%
#65000
0!
0%
0$
1#
#66250
1!
1%
#67500
0!
0%
1$
#68750
1!
1%
#70000
0!
0%
0$
0#
1"
#71250
1!
1%
#72500
0!
0%
1$
#73750
1!
1%
#75000
0!
0%
0$
1#
#76250
1!
1%
#77500
0!
0%
1$
#78750
1!
1%
#80000
0!
0%
0$
0#
0"
0'
0&
#81250
1%
#82500
0%
1$
#83750
1%
#85000
0%
0$
1#
#86250
1%
#87500
0%
1$
#88750
1%
#90000
1!
0%
0$
0#
1"
#91250
1%
#92500
0%
1$
#93750
1%
#95000
0%
0$
1#
#96250
1%
#97500
0%
1$
#98750
1%
#100000
0!
0%
0$
0#
0"
1'
