Assignment_1/1f/fulladder.v

module halfadder ( a,b , sum,ca);
input a,b;
output sum, ca;
    assign sum=a^b;
    assign ca=a&b;
endmodule


module fulladder(input a,b,ca,output sum,carry );

wire w1, w2,w3;
halfadder h1(a,b,w1,w2);
halfadder h2(w1,ca,sum,w3);

assign carry= w3^w2;

endmodule

Assignment_1/1f/fulladder_tb.v
module fulladder_tb;

reg ta,tb,tca;
wire tsum, carry;

fulladder fa(ta,tb,tca,tsum,carry);

initial 
begin
 tca=0;ta=0;tb=0;
 #10 tca=1;ta=0;tb=0;
 #10 tca=0;ta=0;tb=1;
 #10 tca=1;ta=0;tb=1;
 #10 tca=0;ta=1;tb=0;
 #10 tca=1;ta=1;tb=0;
 #10 tca=0;ta=1;tb=1;
 #10 tca=1;ta=1;tb=1;

end



initial
begin
    $monitor($time,"  a=%b,b=%b, ca=%b,sum=%b,carry=%b",ta,tb,tca,tsum,carry);
    $dumpfile("fulladder.vcd");
    $dumpvars;
    #80 $finish;

end
endmodule

Assignment_1/1f/fulladder.vcd
$date
	Sun Feb 20 09:07:08 2022
$end
$version
	Icarus Verilog
$end
$timescale
	1s
$end
$scope module fulladder_tb $end
$var wire 1 ! tsum $end
$var wire 1 " carry $end
$var reg 1 # ta $end
$var reg 1 $ tb $end
$var reg 1 % tca $end
$scope module fa $end
$var wire 1 # a $end
$var wire 1 $ b $end
$var wire 1 % ca $end
$var wire 1 " carry $end
$var wire 1 & w3 $end
$var wire 1 ' w2 $end
$var wire 1 ( w1 $end
$var wire 1 ! sum $end
$scope module h1 $end
$var wire 1 # a $end
$var wire 1 $ b $end
$var wire 1 ' ca $end
$var wire 1 ( sum $end
$upscope $end
$scope module h2 $end
$var wire 1 ( a $end
$var wire 1 % b $end
$var wire 1 & ca $end
$var wire 1 ! sum $end
$upscope $end
$upscope $end
$upscope $end
$enddefinitions $end
#0
$dumpvars
0(
0'
0&
0%
0$
0#
0"
0!
$end
#10
1!
1%
#20
1(
1!
1$
0%
#30
1"
0!
1&
1%
#40
0"
1!
0&
0$
1#
0%
#50
1"
0!
1&
1%
#60
0(
1'
0!
0&
1$
0%
#70
1!
1%
