Assignment_1/1a/2x1_mux.v
module q2x1_MUX(input s0,a,b, output out);

wire w1,w2,inv_s0;

not a1(inv_s0,s0);
and a2(w1,s0,a);
and a3(w2,inv_s0,b);
or a4(out,w1,w2);


endmodule

Assignment_1/1a/2x1_mux_tb.v
`timescale  1ns/10ps

module mux_tb;

reg s0,a,b;
wire out;

q2x1_MUX DUT(s0,a,b,out);

initial
begin
       


   #10 s0=0;a=0;b=0; 
   #10 s0=0;a=0;b=1; 
   #10 s0=0;a=1;b=0; 
   #10 s0=0;a=1;b=1; 
   #10 s0=1;a=0;b=0; 
   #10 s0=1;a=0;b=1; 
   #10 s0=1;a=1;b=0; 
   #10 s0=1;a=1;b=1; 

end

initial begin
   	$monitor("%g s0=%b a=%b b=%b, out=%b ",$time,s0,a,b,out);

      $dumpfile("q_1a.vcd");
      $dumpvars;
end
endmodule

Assignment_1/1a/q_1a.vcd
$date
	Fri Feb 18 05:48:13 2022
$end
$version
	Icarus Verilog
$end
$timescale
	10ps
$end
$scope module mux_tb $end
$var wire 1 ! out $end
$var reg 1 " a $end
$var reg 1 # b $end
$var reg 1 $ s0 $end
$scope module DUT $end
$var wire 1 " a $end
$var wire 1 # b $end
$var wire 1 % inv_s0 $end
$var wire 1 ! out $end
$var wire 1 $ s0 $end
$var wire 1 & w1 $end
$var wire 1 ' w2 $end
$upscope $end
$upscope $end
$enddefinitions $end
#0
$dumpvars
x'
x&
x%
x$
x#
x"
x!
$end
#1000
0!
0'
1%
0&
0#
0"
0$
#2000
1!
1'
1#
#3000
0!
0'
0#
1"
#4000
1!
1'
1#
#5000
0!
0'
0%
0#
0"
1$
#6000
1#
#7000
1!
1&
0#
1"
#8000
1#
