Assignment_2/q4/RCA.v
module rca (output co, output [BITS-1:0] sum, input [BITS-1:0] a0,a1,input ci);

parameter BITS=8;
wire [BITS:0] carry;
assign carry[0]=ci;


genvar i;
generate for (i=0 ; i<BITS; i=i+1) begin: rca_loop

    wire w1,w2,w3;
    xor x1( w1,a0[i],a1[i]);
    xor x2( sum[i], w1,carry[i]);
    and a1( w2,a0[i],a1[i]);
    and a2( w3,w1,carry[i]);
    or o1( carry[i+1],w2,w3);
end

endgenerate// end of the generate block

assign co=carry[BITS];

endmodule

Assignment_2/q4/testbench.v
module testbench;

wire co;
wire [15:0] sum;
reg [15:0] a0,a1;
reg ci;

defparam DUT.BITS=16;

rca DUT(co, sum, a0, a1,ci);


initial
begin
    ci=0;
    a0=16'b0;
    a1=16'b0;

end

always #1000 a0[15]=~a0[15];
always #1000 a0[14]=~a0[14];
always #1000 a0[13]=~a0[13];
always #1000 a0[12]=~a0[12];
always #1000 a0[11]=~a0[11];
always #1000 a0[10]=~a0[10];
always #1000 a0[9]=~a0[9];
always #1000 a0[8]=~a0[8];
always #1000 a0[7]=~a0[7];
always #500 a0[6]=~a0[6];
always #250 a0[5]=~a0[5];
always #125 a0[4]=~a0[4];
always #62.5 a0[3]=~a0[3];
always #31.25 a0[2]=~a0[2];
always #15.625 a0[1]=~a0[1];
always #7.8125 a0[0]=~a0[0];

always #1000 a1[15]=~a1[15];
always #1000 a1[14]=~a1[14];
always #1000 a1[13]=~a1[13];
always #1000 a1[12]=~a1[12];
always #1000 a1[11]=~a1[11];
always #1000 a1[10]=~a1[10];
always #1000 a1[9]=~a1[9];
always #1000 a1[8]=~a1[8];
always #1000 a1[7]=~a1[7];
always #500 a1[6]=~a1[6];
always #250 a1[5]=~a1[5];
always #125 a1[4]=~a1[4];
always #62.5 a1[3]=~a1[3];
always #31.25 a1[2]=~a1[2];
always #15.625 a1[1]=~a1[1];
always #7.8125 a1[0]=~a1[0];

initial #4000 $finish;

initial begin
    $dumpfile("4.vcd");
    $dumpvars;
    $monitor("%g sum=%b co=%b a0=%8b a1=%8b",$time,sum,co,a0,a1);
end


endmodule

Assignment_2/q4/4.vcd
$date
	Mon Apr 04 22:54:18 2022
$end
$version
	Icarus Verilog
$end
$timescale
	1s
$end
$scope module testbench $end
$var wire 16 ! sum [15:0] $end
$var wire 1 " co $end
$var reg 16 # a0 [15:0] $end
$var reg 16 $ a1 [15:0] $end
$var reg 1 % ci $end
$scope module DUT $end
$var wire 16 & a0 [15:0] $end
$var wire 16 ' a1 [15:0] $end
$var wire 1 % ci $end
$var wire 16 ( sum [15:0] $end
$var wire 1 " co $end
$var wire 17 ) carry [16:0] $end
$scope begin rca_loop[0] $end
$var wire 1 * w1 $end
$var wire 1 + w2 $end
$var wire 1 , w3 $end
$upscope $end
$scope begin rca_loop[1] $end
$var wire 1 - w1 $end
$var wire 1 . w2 $end
$var wire 1 / w3 $end
$upscope $end
$scope begin rca_loop[2] $end
$var wire 1 0 w1 $end
$var wire 1 1 w2 $end
$var wire 1 2 w3 $end
$upscope $end
$scope begin rca_loop[3] $end
$var wire 1 3 w1 $end
$var wire 1 4 w2 $end
$var wire 1 5 w3 $end
$upscope $end
$scope begin rca_loop[4] $end
$var wire 1 6 w1 $end
$var wire 1 7 w2 $end
$var wire 1 8 w3 $end
$upscope $end
$scope begin rca_loop[5] $end
$var wire 1 9 w1 $end
$var wire 1 : w2 $end
$var wire 1 ; w3 $end
$upscope $end
$scope begin rca_loop[6] $end
$var wire 1 < w1 $end
$var wire 1 = w2 $end
$var wire 1 > w3 $end
$upscope $end
$scope begin rca_loop[7] $end
$var wire 1 ? w1 $end
$var wire 1 @ w2 $end
$var wire 1 A w3 $end
$upscope $end
$scope begin rca_loop[8] $end
$var wire 1 B w1 $end
$var wire 1 C w2 $end
$var wire 1 D w3 $end
$upscope $end
$scope begin rca_loop[9] $end
$var wire 1 E w1 $end
$var wire 1 F w2 $end
$var wire 1 G w3 $end
$upscope $end
$scope begin rca_loop[10] $end
$var wire 1 H w1 $end
$var wire 1 I w2 $end
$var wire 1 J w3 $end
$upscope $end
$scope begin rca_loop[11] $end
$var wire 1 K w1 $end
$var wire 1 L w2 $end
$var wire 1 M w3 $end
$upscope $end
$scope begin rca_loop[12] $end
$var wire 1 N w1 $end
$var wire 1 O w2 $end
$var wire 1 P w3 $end
$upscope $end
$scope begin rca_loop[13] $end
$var wire 1 Q w1 $end
$var wire 1 R w2 $end
$var wire 1 S w3 $end
$upscope $end
$scope begin rca_loop[14] $end
$var wire 1 T w1 $end
$var wire 1 U w2 $end
$var wire 1 V w3 $end
$upscope $end
$scope begin rca_loop[15] $end
$var wire 1 W w1 $end
$var wire 1 X w2 $end
$var wire 1 Y w3 $end
$upscope $end
$upscope $end
$upscope $end
$enddefinitions $end
#0
$dumpvars
0Y
0X
0W
0V
0U
0T
0S
0R
0Q
0P
0O
0N
0M
0L
0K
0J
0I
0H
0G
0F
0E
0D
0C
0B
0A
0@
0?
0>
0=
0<
0;
0:
09
08
07
06
05
04
03
02
01
00
0/
0.
0-
0,
0+
0*
b0 )
b0 (
b0 '
b0 &
0%
b0 $
b0 #
0"
b0 !
$end
#8
b10 !
b10 (
b10 )
1+
b1 $
b1 '
b1 #
b1 &
#16
b100 !
b100 (
b100 )
0+
1.
b10 $
b10 '
b10 #
b10 &
#24
b110 !
b110 (
b110 )
1+
b11 $
b11 '
b11 #
b11 &
#31
b1110 !
b1110 (
b1110 )
11
b111 $
b111 '
b111 #
b111 &
#32
b1000 !
b1000 (
b1000 )
0+
0.
b100 $
b100 '
b100 #
b100 &
#40
b1010 !
b1010 (
b1010 )
1+
b101 $
b101 '
b101 #
b101 &
#48
b1100 !
b1100 (
b1100 )
0+
1.
b110 $
b110 '
b110 #
b110 &
#56
b1110 !
b1110 (
b1110 )
1+
b111 $
b111 '
b111 #
b111 &
#62
b110 !
b110 (
b110 )
01
b11 $
b11 '
b11 #
b11 &
#63
b10110 !
b10110 (
b10110 )
14
b1011 $
b1011 '
b1011 #
b1011 &
#64
b10000 !
b10000 (
b10000 )
0+
0.
b1000 $
b1000 '
b1000 #
b1000 &
#72
b10010 !
b10010 (
b10010 )
1+
b1001 $
b1001 '
b1001 #
b1001 &
#80
b10100 !
b10100 (
b10100 )
0+
1.
b1010 $
b1010 '
b1010 #
b1010 &
#88
b10110 !
b10110 (
b10110 )
1+
b1011 $
b1011 '
b1011 #
b1011 &
#93
b11110 !
b11110 (
b11110 )
11
b1111 $
b1111 '
b1111 #
b1111 &
#96
b11000 !
b11000 (
b11000 )
0+
0.
b1100 $
b1100 '
b1100 #
b1100 &
#104
b11010 !
b11010 (
b11010 )
1+
b1101 $
b1101 '
b1101 #
b1101 &
#112
b11100 !
b11100 (
b11100 )
0+
1.
b1110 $
b1110 '
b1110 #
b1110 &
#120
b11110 !
b11110 (
b11110 )
1+
b1111 $
b1111 '
b1111 #
b1111 &
#124
b10110 !
b10110 (
b10110 )
01
b1011 $
b1011 '
b1011 #
b1011 &
#125
b110110 !
b110110 (
b110110 )
17
b11011 $
b11011 '
b11011 #
b11011 &
#126
b100110 !
b100110 (
b100110 )
04
b10011 $
b10011 '
b10011 #
b10011 &
#128
b100000 !
b100000 (
b100000 )
0+
0.
b10000 $
b10000 '
b10000 #
b10000 &
#136
b100010 !
b100010 (
b100010 )
1+
b10001 $
b10001 '
b10001 #
b10001 &
#144
b100100 !
b100100 (
b100100 )
0+
1.
b10010 $
b10010 '
b10010 #
b10010 &
#152
b100110 !
b100110 (
b100110 )
1+
b10011 $
b10011 '
b10011 #
b10011 &
#155
b101110 !
b101110 (
b101110 )
11
b10111 $
b10111 '
b10111 #
b10111 &
#160
b101000 !
b101000 (
b101000 )
0+
0.
b10100 $
b10100 '
b10100 #
b10100 &
#168
b101010 !
b101010 (
b101010 )
1+
b10101 $
b10101 '
b10101 #
b10101 &
#176
b101100 !
b101100 (
b101100 )
0+
1.
b10110 $
b10110 '
b10110 #
b10110 &
#184
b101110 !
b101110 (
b101110 )
1+
b10111 $
b10111 '
b10111 #
b10111 &
#186
b100110 !
b100110 (
b100110 )
01
b10011 $
b10011 '
b10011 #
b10011 &
#189
b110110 !
b110110 (
b110110 )
14
b11011 $
b11011 '
b11011 #
b11011 &
#192
b110000 !
b110000 (
b110000 )
0+
0.
b11000 $
b11000 '
b11000 #
b11000 &
#200
b110010 !
b110010 (
b110010 )
1+
b11001 $
b11001 '
b11001 #
b11001 &
#208
b110100 !
b110100 (
b110100 )
0+
1.
b11010 $
b11010 '
b11010 #
b11010 &
#216
b110110 !
b110110 (
b110110 )
1+
b11011 $
b11011 '
b11011 #
b11011 &
#217
b111110 !
b111110 (
b111110 )
11
b11111 $
b11111 '
b11111 #
b11111 &
#224
b111000 !
b111000 (
b111000 )
0+
0.
b11100 $
b11100 '
b11100 #
b11100 &
#232
b111010 !
b111010 (
b111010 )
1+
b11101 $
b11101 '
b11101 #
b11101 &
#240
b111100 !
b111100 (
b111100 )
0+
1.
b11110 $
b11110 '
b11110 #
b11110 &
#248
b110110 !
b110110 (
b110110 )
1+
01
b11011 $
b11011 '
b11011 #
b11011 &
#250
b1010110 !
b1010110 (
b1010110 )
07
1:
b101011 $
b101011 '
b101011 #
b101011 &
#252
b1000110 !
b1000110 (
b1000110 )
04
b100011 $
b100011 '
b100011 #
b100011 &
#256
b1000000 !
b1000000 (
b1000000 )
0+
0.
b100000 $
b100000 '
b100000 #
b100000 &
#264
b1000010 !
b1000010 (
b1000010 )
1+
b100001 $
b100001 '
b100001 #
b100001 &
#272
b1000100 !
b1000100 (
b1000100 )
0+
1.
b100010 $
b100010 '
b100010 #
b100010 &
#279
b1001100 !
b1001100 (
b1001100 )
11
b100110 $
b100110 '
b100110 #
b100110 &
#280
b1001110 !
b1001110 (
b1001110 )
1+
b100111 $
b100111 '
b100111 #
b100111 &
#288
b1001000 !
b1001000 (
b1001000 )
0+
0.
b100100 $
b100100 '
b100100 #
b100100 &
#296
b1001010 !
b1001010 (
b1001010 )
1+
b100101 $
b100101 '
b100101 #
b100101 &
#304
b1001100 !
b1001100 (
b1001100 )
0+
1.
b100110 $
b100110 '
b100110 #
b100110 &
#310
b1000100 !
b1000100 (
b1000100 )
01
b100010 $
b100010 '
b100010 #
b100010 &
#312
b1000110 !
b1000110 (
b1000110 )
1+
b100011 $
b100011 '
b100011 #
b100011 &
#315
b1010110 !
b1010110 (
b1010110 )
14
b101011 $
b101011 '
b101011 #
b101011 &
#320
b1010000 !
b1010000 (
b1010000 )
0+
0.
b101000 $
b101000 '
b101000 #
b101000 &
#328
b1010010 !
b1010010 (
b1010010 )
1+
b101001 $
b101001 '
b101001 #
b101001 &
#336
b1010100 !
b1010100 (
b1010100 )
0+
1.
b101010 $
b101010 '
b101010 #
b101010 &
#341
b1011100 !
b1011100 (
b1011100 )
11
b101110 $
b101110 '
b101110 #
b101110 &
#344
b1011110 !
b1011110 (
b1011110 )
1+
b101111 $
b101111 '
b101111 #
b101111 &
#352
b1011000 !
b1011000 (
b1011000 )
0+
0.
b101100 $
b101100 '
b101100 #
b101100 &
#360
b1011010 !
b1011010 (
b1011010 )
1+
b101101 $
b101101 '
b101101 #
b101101 &
#368
b1011100 !
b1011100 (
b1011100 )
0+
1.
b101110 $
b101110 '
b101110 #
b101110 &
#372
b1010100 !
b1010100 (
b1010100 )
01
b101010 $
b101010 '
b101010 #
b101010 &
#375
b1110100 !
b1110100 (
b1110100 )
17
b111010 $
b111010 '
b111010 #
b111010 &
#376
b1110110 !
b1110110 (
b1110110 )
1+
b111011 $
b111011 '
b111011 #
b111011 &
#378
b1100110 !
b1100110 (
b1100110 )
04
b110011 $
b110011 '
b110011 #
b110011 &
#384
b1100000 !
b1100000 (
b1100000 )
0+
0.
b110000 $
b110000 '
b110000 #
b110000 &
#392
b1100010 !
b1100010 (
b1100010 )
1+
b110001 $
b110001 '
b110001 #
b110001 &
#400
b1100100 !
b1100100 (
b1100100 )
0+
1.
b110010 $
b110010 '
b110010 #
b110010 &
#403
b1101100 !
b1101100 (
b1101100 )
11
b110110 $
b110110 '
b110110 #
b110110 &
#408
b1101110 !
b1101110 (
b1101110 )
1+
b110111 $
b110111 '
b110111 #
b110111 &
#416
b1101000 !
b1101000 (
b1101000 )
0+
0.
b110100 $
b110100 '
b110100 #
b110100 &
#424
b1101010 !
b1101010 (
b1101010 )
1+
b110101 $
b110101 '
b110101 #
b110101 &
#432
b1101100 !
b1101100 (
b1101100 )
0+
1.
b110110 $
b110110 '
b110110 #
b110110 &
#434
b1100100 !
b1100100 (
b1100100 )
01
b110010 $
b110010 '
b110010 #
b110010 &
#440
b1100110 !
b1100110 (
b1100110 )
1+
b110011 $
b110011 '
b110011 #
b110011 &
#441
b1110110 !
b1110110 (
b1110110 )
14
b111011 $
b111011 '
b111011 #
b111011 &
#448
b1110000 !
b1110000 (
b1110000 )
0+
0.
b111000 $
b111000 '
b111000 #
b111000 &
#456
b1110010 !
b1110010 (
b1110010 )
1+
b111001 $
b111001 '
b111001 #
b111001 &
#464
b1110100 !
b1110100 (
b1110100 )
0+
1.
b111010 $
b111010 '
b111010 #
b111010 &
#465
b1111100 !
b1111100 (
b1111100 )
11
b111110 $
b111110 '
b111110 #
b111110 &
#472
b1111110 !
b1111110 (
b1111110 )
1+
b111111 $
b111111 '
b111111 #
b111111 &
#480
b1111000 !
b1111000 (
b1111000 )
0+
0.
b111100 $
b111100 '
b111100 #
b111100 &
#488
b1111010 !
b1111010 (
b1111010 )
1+
b111101 $
b111101 '
b111101 #
b111101 &
#496
b1110100 !
b1110100 (
b1110100 )
0+
1.
01
b111010 $
b111010 '
b111010 #
b111010 &
#500
b10010100 !
b10010100 (
b10010100 )
07
0:
1=
b1001010 $
b1001010 '
b1001010 #
b1001010 &
#504
b10000110 !
b10000110 (
b10000110 )
1+
04
b1000011 $
b1000011 '
b1000011 #
b1000011 &
#512
b10000000 !
b10000000 (
b10000000 )
0+
0.
b1000000 $
b1000000 '
b1000000 #
b1000000 &
#520
b10000010 !
b10000010 (
b10000010 )
1+
b1000001 $
b1000001 '
b1000001 #
b1000001 &
#527
b10001010 !
b10001010 (
b10001010 )
11
b1000101 $
b1000101 '
b1000101 #
b1000101 &
#528
b10001100 !
b10001100 (
b10001100 )
0+
1.
b1000110 $
b1000110 '
b1000110 #
b1000110 &
#536
b10001110 !
b10001110 (
b10001110 )
1+
b1000111 $
b1000111 '
b1000111 #
b1000111 &
#544
b10001000 !
b10001000 (
b10001000 )
0+
0.
b1000100 $
b1000100 '
b1000100 #
b1000100 &
#552
b10001010 !
b10001010 (
b10001010 )
1+
b1000101 $
b1000101 '
b1000101 #
b1000101 &
#558
b10000010 !
b10000010 (
b10000010 )
01
b1000001 $
b1000001 '
b1000001 #
b1000001 &
#560
b10000100 !
b10000100 (
b10000100 )
0+
1.
b1000010 $
b1000010 '
b1000010 #
b1000010 &
#567
b10010100 !
b10010100 (
b10010100 )
14
b1001010 $
b1001010 '
b1001010 #
b1001010 &
#568
b10010110 !
b10010110 (
b10010110 )
1+
b1001011 $
b1001011 '
b1001011 #
b1001011 &
#576
b10010000 !
b10010000 (
b10010000 )
0+
0.
b1001000 $
b1001000 '
b1001000 #
b1001000 &
#584
b10010010 !
b10010010 (
b10010010 )
1+
b1001001 $
b1001001 '
b1001001 #
b1001001 &
#589
b10011010 !
b10011010 (
b10011010 )
11
b1001101 $
b1001101 '
b1001101 #
b1001101 &
#592
b10011100 !
b10011100 (
b10011100 )
0+
1.
b1001110 $
b1001110 '
b1001110 #
b1001110 &
#600
b10011110 !
b10011110 (
b10011110 )
1+
b1001111 $
b1001111 '
b1001111 #
b1001111 &
#608
b10011000 !
b10011000 (
b10011000 )
0+
0.
b1001100 $
b1001100 '
b1001100 #
b1001100 &
#616
b10011010 !
b10011010 (
b10011010 )
1+
b1001101 $
b1001101 '
b1001101 #
b1001101 &
#620
b10010010 !
b10010010 (
b10010010 )
01
b1001001 $
b1001001 '
b1001001 #
b1001001 &
#624
b10010100 !
b10010100 (
b10010100 )
0+
1.
b1001010 $
b1001010 '
b1001010 #
b1001010 &
#625
b10110100 !
b10110100 (
b10110100 )
17
b1011010 $
b1011010 '
b1011010 #
b1011010 &
#630
b10100100 !
b10100100 (
b10100100 )
04
b1010010 $
b1010010 '
b1010010 #
b1010010 &
#632
b10100110 !
b10100110 (
b10100110 )
1+
b1010011 $
b1010011 '
b1010011 #
b1010011 &
#640
b10100000 !
b10100000 (
b10100000 )
0+
0.
b1010000 $
b1010000 '
b1010000 #
b1010000 &
#648
b10100010 !
b10100010 (
b10100010 )
1+
b1010001 $
b1010001 '
b1010001 #
b1010001 &
#651
b10101010 !
b10101010 (
b10101010 )
11
b1010101 $
b1010101 '
b1010101 #
b1010101 &
#656
b10101100 !
b10101100 (
b10101100 )
0+
1.
b1010110 $
b1010110 '
b1010110 #
b1010110 &
#664
b10101110 !
b10101110 (
b10101110 )
1+
b1010111 $
b1010111 '
b1010111 #
b1010111 &
#672
b10101000 !
b10101000 (
b10101000 )
0+
0.
b1010100 $
b1010100 '
b1010100 #
b1010100 &
#680
b10101010 !
b10101010 (
b10101010 )
1+
b1010101 $
b1010101 '
b1010101 #
b1010101 &
#682
b10100010 !
b10100010 (
b10100010 )
01
b1010001 $
b1010001 '
b1010001 #
b1010001 &
#688
b10100100 !
b10100100 (
b10100100 )
0+
1.
b1010010 $
b1010010 '
b1010010 #
b1010010 &
#693
b10110100 !
b10110100 (
b10110100 )
14
b1011010 $
b1011010 '
b1011010 #
b1011010 &
#696
b10110110 !
b10110110 (
b10110110 )
1+
b1011011 $
b1011011 '
b1011011 #
b1011011 &
#704
b10110000 !
b10110000 (
b10110000 )
0+
0.
b1011000 $
b1011000 '
b1011000 #
b1011000 &
#712
b10110010 !
b10110010 (
b10110010 )
1+
b1011001 $
b1011001 '
b1011001 #
b1011001 &
#713
b10111010 !
b10111010 (
b10111010 )
11
b1011101 $
b1011101 '
b1011101 #
b1011101 &
#720
b10111100 !
b10111100 (
b10111100 )
0+
1.
b1011110 $
b1011110 '
b1011110 #
b1011110 &
#728
b10111110 !
b10111110 (
b10111110 )
1+
b1011111 $
b1011111 '
b1011111 #
b1011111 &
#736
b10111000 !
b10111000 (
b10111000 )
0+
0.
b1011100 $
b1011100 '
b1011100 #
b1011100 &
#744
b10110010 !
b10110010 (
b10110010 )
1+
01
b1011001 $
b1011001 '
b1011001 #
b1011001 &
#750
b11010010 !
b11010010 (
b11010010 )
07
1:
b1101001 $
b1101001 '
b1101001 #
b1101001 &
#752
b11010100 !
b11010100 (
b11010100 )
0+
1.
b1101010 $
b1101010 '
b1101010 #
b1101010 &
#756
b11000100 !
b11000100 (
b11000100 )
04
b1100010 $
b1100010 '
b1100010 #
b1100010 &
#760
b11000110 !
b11000110 (
b11000110 )
1+
b1100011 $
b1100011 '
b1100011 #
b1100011 &
#768
b11000000 !
b11000000 (
b11000000 )
0+
0.
b1100000 $
b1100000 '
b1100000 #
b1100000 &
#775
b11001000 !
b11001000 (
b11001000 )
11
b1100100 $
b1100100 '
b1100100 #
b1100100 &
#776
b11001010 !
b11001010 (
b11001010 )
1+
b1100101 $
b1100101 '
b1100101 #
b1100101 &
#784
b11001100 !
b11001100 (
b11001100 )
0+
1.
b1100110 $
b1100110 '
b1100110 #
b1100110 &
#792
b11001110 !
b11001110 (
b11001110 )
1+
b1100111 $
b1100111 '
b1100111 #
b1100111 &
#800
b11001000 !
b11001000 (
b11001000 )
0+
0.
b1100100 $
b1100100 '
b1100100 #
b1100100 &
#806
b11000000 !
b11000000 (
b11000000 )
01
b1100000 $
b1100000 '
b1100000 #
b1100000 &
#808
b11000010 !
b11000010 (
b11000010 )
1+
b1100001 $
b1100001 '
b1100001 #
b1100001 &
#816
b11000100 !
b11000100 (
b11000100 )
0+
1.
b1100010 $
b1100010 '
b1100010 #
b1100010 &
#819
b11010100 !
b11010100 (
b11010100 )
14
b1101010 $
b1101010 '
b1101010 #
b1101010 &
#824
b11010110 !
b11010110 (
b11010110 )
1+
b1101011 $
b1101011 '
b1101011 #
b1101011 &
#832
b11010000 !
b11010000 (
b11010000 )
0+
0.
b1101000 $
b1101000 '
b1101000 #
b1101000 &
#837
b11011000 !
b11011000 (
b11011000 )
11
b1101100 $
b1101100 '
b1101100 #
b1101100 &
#840
b11011010 !
b11011010 (
b11011010 )
1+
b1101101 $
b1101101 '
b1101101 #
b1101101 &
#848
b11011100 !
b11011100 (
b11011100 )
0+
1.
b1101110 $
b1101110 '
b1101110 #
b1101110 &
#856
b11011110 !
b11011110 (
b11011110 )
1+
b1101111 $
b1101111 '
b1101111 #
b1101111 &
#864
b11011000 !
b11011000 (
b11011000 )
0+
0.
b1101100 $
b1101100 '
b1101100 #
b1101100 &
#868
b11010000 !
b11010000 (
b11010000 )
01
b1101000 $
b1101000 '
b1101000 #
b1101000 &
#872
b11010010 !
b11010010 (
b11010010 )
1+
b1101001 $
b1101001 '
b1101001 #
b1101001 &
#875
b11110010 !
b11110010 (
b11110010 )
17
b1111001 $
b1111001 '
b1111001 #
b1111001 &
#880
b11110100 !
b11110100 (
b11110100 )
0+
1.
b1111010 $
b1111010 '
b1111010 #
b1111010 &
#882
b11100100 !
b11100100 (
b11100100 )
04
b1110010 $
b1110010 '
b1110010 #
b1110010 &
#888
b11100110 !
b11100110 (
b11100110 )
1+
b1110011 $
b1110011 '
b1110011 #
b1110011 &
#896
b11100000 !
b11100000 (
b11100000 )
0+
0.
b1110000 $
b1110000 '
b1110000 #
b1110000 &
#899
b11101000 !
b11101000 (
b11101000 )
11
b1110100 $
b1110100 '
b1110100 #
b1110100 &
#904
b11101010 !
b11101010 (
b11101010 )
1+
b1110101 $
b1110101 '
b1110101 #
b1110101 &
#912
b11101100 !
b11101100 (
b11101100 )
0+
1.
b1110110 $
b1110110 '
b1110110 #
b1110110 &
#920
b11101110 !
b11101110 (
b11101110 )
1+
b1110111 $
b1110111 '
b1110111 #
b1110111 &
#928
b11101000 !
b11101000 (
b11101000 )
0+
0.
b1110100 $
b1110100 '
b1110100 #
b1110100 &
#930
b11100000 !
b11100000 (
b11100000 )
01
b1110000 $
b1110000 '
b1110000 #
b1110000 &
#936
b11100010 !
b11100010 (
b11100010 )
1+
b1110001 $
b1110001 '
b1110001 #
b1110001 &
#944
b11100100 !
b11100100 (
b11100100 )
0+
1.
b1110010 $
b1110010 '
b1110010 #
b1110010 &
#945
b11110100 !
b11110100 (
b11110100 )
14
b1111010 $
b1111010 '
b1111010 #
b1111010 &
#952
b11110110 !
b11110110 (
b11110110 )
1+
b1111011 $
b1111011 '
b1111011 #
b1111011 &
#960
b11110000 !
b11110000 (
b11110000 )
0+
0.
b1111000 $
b1111000 '
b1111000 #
b1111000 &
#961
b11111000 !
b11111000 (
b11111000 )
11
b1111100 $
b1111100 '
b1111100 #
b1111100 &
#968
b11111010 !
b11111010 (
b11111010 )
1+
b1111101 $
b1111101 '
b1111101 #
b1111101 &
#976
b11111100 !
b11111100 (
b11111100 )
0+
1.
b1111110 $
b1111110 '
b1111110 #
b1111110 &
#984
b11111110 !
b11111110 (
b11111110 )
1+
b1111111 $
b1111111 '
b1111111 #
b1111111 &
#992
b11110000 !
b11110000 (
b11110000 )
0+
0.
01
b1111000 $
b1111000 '
b1111000 #
b1111000 &
#1000
b1111111100010010 !
b1111111100010010 (
1"
b11111111100010010 )
1+
07
0:
0=
1@
1C
1F
1I
1L
1O
1R
1U
1X
b1111111110001001 $
b1111111110001001 '
b1111111110001001 #
b1111111110001001 &
#1008
b1111111100000100 !
b1111111100000100 (
b11111111100000100 )
0+
1.
04
b1111111110000010 $
b1111111110000010 '
b1111111110000010 #
b1111111110000010 &
#1016
b1111111100000110 !
b1111111100000110 (
b11111111100000110 )
1+
b1111111110000011 $
b1111111110000011 '
b1111111110000011 #
b1111111110000011 &
#1023
b1111111100001110 !
b1111111100001110 (
b11111111100001110 )
11
b1111111110000111 $
b1111111110000111 '
b1111111110000111 #
b1111111110000111 &
#1024
b1111111100001000 !
b1111111100001000 (
b11111111100001000 )
0+
0.
b1111111110000100 $
b1111111110000100 '
b1111111110000100 #
b1111111110000100 &
#1032
b1111111100001010 !
b1111111100001010 (
b11111111100001010 )
1+
b1111111110000101 $
b1111111110000101 '
b1111111110000101 #
b1111111110000101 &
#1040
b1111111100001100 !
b1111111100001100 (
b11111111100001100 )
0+
1.
b1111111110000110 $
b1111111110000110 '
b1111111110000110 #
b1111111110000110 &
#1048
b1111111100001110 !
b1111111100001110 (
b11111111100001110 )
1+
b1111111110000111 $
b1111111110000111 '
b1111111110000111 #
b1111111110000111 &
#1054
b1111111100000110 !
b1111111100000110 (
b11111111100000110 )
01
b1111111110000011 $
b1111111110000011 '
b1111111110000011 #
b1111111110000011 &
#1056
b1111111100000000 !
b1111111100000000 (
b11111111100000000 )
0+
0.
b1111111110000000 $
b1111111110000000 '
b1111111110000000 #
b1111111110000000 &
#1064
b1111111100000010 !
b1111111100000010 (
b11111111100000010 )
1+
b1111111110000001 $
b1111111110000001 '
b1111111110000001 #
b1111111110000001 &
#1071
b1111111100010010 !
b1111111100010010 (
b11111111100010010 )
14
b1111111110001001 $
b1111111110001001 '
b1111111110001001 #
b1111111110001001 &
#1072
b1111111100010100 !
b1111111100010100 (
b11111111100010100 )
0+
1.
b1111111110001010 $
b1111111110001010 '
b1111111110001010 #
b1111111110001010 &
#1080
b1111111100010110 !
b1111111100010110 (
b11111111100010110 )
1+
b1111111110001011 $
b1111111110001011 '
b1111111110001011 #
b1111111110001011 &
#1085
b1111111100011110 !
b1111111100011110 (
b11111111100011110 )
11
b1111111110001111 $
b1111111110001111 '
b1111111110001111 #
b1111111110001111 &
#1088
b1111111100011000 !
b1111111100011000 (
b11111111100011000 )
0+
0.
b1111111110001100 $
b1111111110001100 '
b1111111110001100 #
b1111111110001100 &
#1096
b1111111100011010 !
b1111111100011010 (
b11111111100011010 )
1+
b1111111110001101 $
b1111111110001101 '
b1111111110001101 #
b1111111110001101 &
#1104
b1111111100011100 !
b1111111100011100 (
b11111111100011100 )
0+
1.
b1111111110001110 $
b1111111110001110 '
b1111111110001110 #
b1111111110001110 &
#1112
b1111111100011110 !
b1111111100011110 (
b11111111100011110 )
1+
b1111111110001111 $
b1111111110001111 '
b1111111110001111 #
b1111111110001111 &
#1116
b1111111100010110 !
b1111111100010110 (
b11111111100010110 )
01
b1111111110001011 $
b1111111110001011 '
b1111111110001011 #
b1111111110001011 &
#1120
b1111111100010000 !
b1111111100010000 (
b11111111100010000 )
0+
0.
b1111111110001000 $
b1111111110001000 '
b1111111110001000 #
b1111111110001000 &
#1125
b1111111100110000 !
b1111111100110000 (
b11111111100110000 )
17
b1111111110011000 $
b1111111110011000 '
b1111111110011000 #
b1111111110011000 &
#1128
b1111111100110010 !
b1111111100110010 (
b11111111100110010 )
1+
b1111111110011001 $
b1111111110011001 '
b1111111110011001 #
b1111111110011001 &
#1134
b1111111100100010 !
b1111111100100010 (
b11111111100100010 )
04
b1111111110010001 $
b1111111110010001 '
b1111111110010001 #
b1111111110010001 &
#1136
b1111111100100100 !
b1111111100100100 (
b11111111100100100 )
0+
1.
b1111111110010010 $
b1111111110010010 '
b1111111110010010 #
b1111111110010010 &
#1144
b1111111100100110 !
b1111111100100110 (
b11111111100100110 )
1+
b1111111110010011 $
b1111111110010011 '
b1111111110010011 #
b1111111110010011 &
#1147
b1111111100101110 !
b1111111100101110 (
b11111111100101110 )
11
b1111111110010111 $
b1111111110010111 '
b1111111110010111 #
b1111111110010111 &
#1152
b1111111100101000 !
b1111111100101000 (
b11111111100101000 )
0+
0.
b1111111110010100 $
b1111111110010100 '
b1111111110010100 #
b1111111110010100 &
#1160
b1111111100101010 !
b1111111100101010 (
b11111111100101010 )
1+
b1111111110010101 $
b1111111110010101 '
b1111111110010101 #
b1111111110010101 &
#1168
b1111111100101100 !
b1111111100101100 (
b11111111100101100 )
0+
1.
b1111111110010110 $
b1111111110010110 '
b1111111110010110 #
b1111111110010110 &
#1176
b1111111100101110 !
b1111111100101110 (
b11111111100101110 )
1+
b1111111110010111 $
b1111111110010111 '
b1111111110010111 #
b1111111110010111 &
#1178
b1111111100100110 !
b1111111100100110 (
b11111111100100110 )
01
b1111111110010011 $
b1111111110010011 '
b1111111110010011 #
b1111111110010011 &
#1184
b1111111100100000 !
b1111111100100000 (
b11111111100100000 )
0+
0.
b1111111110010000 $
b1111111110010000 '
b1111111110010000 #
b1111111110010000 &
#1192
b1111111100100010 !
b1111111100100010 (
b11111111100100010 )
1+
b1111111110010001 $
b1111111110010001 '
b1111111110010001 #
b1111111110010001 &
#1197
b1111111100110010 !
b1111111100110010 (
b11111111100110010 )
14
b1111111110011001 $
b1111111110011001 '
b1111111110011001 #
b1111111110011001 &
#1200
b1111111100110100 !
b1111111100110100 (
b11111111100110100 )
0+
1.
b1111111110011010 $
b1111111110011010 '
b1111111110011010 #
b1111111110011010 &
#1208
b1111111100110110 !
b1111111100110110 (
b11111111100110110 )
1+
b1111111110011011 $
b1111111110011011 '
b1111111110011011 #
b1111111110011011 &
#1209
b1111111100111110 !
b1111111100111110 (
b11111111100111110 )
11
b1111111110011111 $
b1111111110011111 '
b1111111110011111 #
b1111111110011111 &
#1216
b1111111100111000 !
b1111111100111000 (
b11111111100111000 )
0+
0.
b1111111110011100 $
b1111111110011100 '
b1111111110011100 #
b1111111110011100 &
#1224
b1111111100111010 !
b1111111100111010 (
b11111111100111010 )
1+
b1111111110011101 $
b1111111110011101 '
b1111111110011101 #
b1111111110011101 &
