Assignment_1/3/multifunctiongate.v
module multifunctiongate( a,b,c,d , F);

input a,b,c,d;
output F;

wire inv_a,inv_c,inv_d;
wire w1,w2,w3,w4;

not n1(inv_a,a);
not n2(inv_d,d);
not n3(inv_c,c);

and a1(w1,inv_a,c,d);
and a2(w2,inv_c,b,d);
and a3(w3,b,c,inv_d);
and a4(w4,a,inv_c,inv_d);

or o1(F,w1,w2,w3,w4);


endmodule

Assignment_1/3/testbench.v
`timescale  1ns/10ps

module testbench;

reg x,y,a,b;
wire out;

multifunctiongate DUT(x,y,a,b,out);


initial begin
    
    a=1'b0;    
    b=1'b0;        
    x=1'b0;    
    y=1'b0;    
    #200 $finish;
end

always #100 x= ~x;
always #50   y= ~y;
always #25 a= ~a;
always #12.5 b= ~b;

initial begin
   	$monitor("%g Output=%b x=%b y=%b a=%b b=%b ",$time,out,x,y,a,b);

    $dumpfile("q_3.vcd");
    $dumpvars;
end
endmodule

Assignment_1/3/q_3.vcd
$date
	Sun Feb 20 19:53:13 2022
$end
$version
	Icarus Verilog
$end
$timescale
	10ps
$end
$scope module testbench $end
$var wire 1 ! out $end
$var reg 1 " a $end
$var reg 1 # b $end
$var reg 1 $ x $end
$var reg 1 % y $end
$scope module DUT $end
$var wire 1 ! F $end
$var wire 1 $ a $end
$var wire 1 % b $end
$var wire 1 " c $end
$var wire 1 # d $end
$var wire 1 & inv_a $end
$var wire 1 ' inv_c $end
$var wire 1 ( inv_d $end
$var wire 1 ) w1 $end
$var wire 1 * w2 $end
$var wire 1 + w3 $end
$var wire 1 , w4 $end
$upscope $end
$upscope $end
$enddefinitions $end
#0
$dumpvars
0,
0+
0*
0)
1(
1'
1&
0%
0$
0#
0"
0!
$end
#1250
0(
1#
#2500
1(
0'
0#
1"
#3750
1!
0(
1)
1#
#5000
0!
1(
1'
0)
0#
0"
1%
#6250
1!
0(
1*
1#
#7500
1+
1!
1(
0*
0'
0#
1"
#8750
0+
0(
1)
1#
#10000
1,
1!
1(
1'
0)
0&
0#
0"
0%
1$
#11250
0!
0,
0(
1#
#12500
1(
0'
0#
1"
#13750
0(
1#
#15000
1!
1,
1(
1'
0#
0"
1%
#16250
0,
0(
1*
1#
#17500
1+
1!
1(
0*
0'
0#
1"
#18750
0!
0+
0(
1#
#20000
1(
1'
1&
0#
0"
0%
0$
