Assignment_1/4b/4_Bit_updowncounter.v
module updowncounter(clk,rst,s,count);

input clk,rst,s;// s =0 for count down and vice versa

output reg [3:0] count;

initial count=4'b0000;


always @(posedge (clk) or posedge(rst))
begin
if (rst==1'b1)
    count<=0;
else
    if (s==1)
    count<=count+1;
    else
    count<=count-1;

end


endmodule

Assignment_1/4b/testbench.v
`timescale 1ps/1ps

module testbench;
reg clk,rst,s;
wire [3:0] out;
updowncounter DUT(clk,rst,s,out);


initial begin
    clk=1'b0;
    rst=1'b0;
    s=1'b0;
    #1600 $finish;
end

always #5 clk=~clk;
always #400 rst=~rst;
always #800 s=~s;


initial begin
    $dumpfile("4b.vcd");
    $dumpvars;
    $monitor("%g clk=%b rst=%2b s=%b, count=%4b",$time,clk, rst,s, out);
end

endmodule

Assignment_1/4b/4b.vcd
$date
	Sun Feb 20 22:47:42 2022
$end
$version
	Icarus Verilog
$end
$timescale
	1ps
$end
$scope module testbench $end
$var wire 4 ! out [3:0] $end
$var reg 1 " clk $end
$var reg 1 # rst $end
$var reg 1 $ s $end
$scope module DUT $end
$var wire 1 " clk $end
$var wire 1 # rst $end
$var wire 1 $ s $end
$var reg 4 % count [3:0] $end
$upscope $end
$upscope $end
$enddefinitions $end
#0
$dumpvars
b0 %
0$
0#
0"
b0 !
$end
#5
b1111 !
b1111 %
1"
#10
0"
#15
b1110 !
b1110 %
1"
#20
0"
#25
b1101 !
b1101 %
1"
#30
0"
#35
b1100 !
b1100 %
1"
#40
0"
#45
b1011 !
b1011 %
1"
#50
0"
#55
b1010 !
b1010 %
1"
#60
0"
#65
b1001 !
b1001 %
1"
#70
0"
#75
b1000 !
b1000 %
1"
#80
0"
#85
b111 !
b111 %
1"
#90
0"
#95
b110 !
b110 %
1"
#100
0"
#105
b101 !
b101 %
1"
#110
0"
#115
b100 !
b100 %
1"
#120
0"
#125
b11 !
b11 %
1"
#130
0"
#135
b10 !
b10 %
1"
#140
0"
#145
b1 !
b1 %
1"
#150
0"
#155
b0 !
b0 %
1"
#160
0"
#165
b1111 !
b1111 %
1"
#170
0"
#175
b1110 !
b1110 %
1"
#180
0"
#185
b1101 !
b1101 %
1"
#190
0"
#195
b1100 !
b1100 %
1"
#200
0"
#205
b1011 !
b1011 %
1"
#210
0"
#215
b1010 !
b1010 %
1"
#220
0"
#225
b1001 !
b1001 %
1"
#230
0"
#235
b1000 !
b1000 %
1"
#240
0"
#245
b111 !
b111 %
1"
#250
0"
#255
b110 !
b110 %
1"
#260
0"
#265
b101 !
b101 %
1"
#270
0"
#275
b100 !
b100 %
1"
#280
0"
#285
b11 !
b11 %
1"
#290
0"
#295
b10 !
b10 %
1"
#300
0"
#305
b1 !
b1 %
1"
#310
0"
#315
b0 !
b0 %
1"
#320
0"
#325
b1111 !
b1111 %
1"
#330
0"
#335
b1110 !
b1110 %
1"
#340
0"
#345
b1101 !
b1101 %
1"
#350
0"
#355
b1100 !
b1100 %
1"
#360
0"
#365
b1011 !
b1011 %
1"
#370
0"
#375
b1010 !
b1010 %
1"
#380
0"
#385
b1001 !
b1001 %
1"
#390
0"
#395
b1000 !
b1000 %
1"
#400
b0 !
b0 %
0"
1#
