Assignment_1/1d/8x1mux.v
module q2x1_MUX(input s0,a,b, output out);
wire w1,w2,inv_s0;
not a1(inv_s0,s0);
and a2(w1,inv_s0,a);
and a3(w2,s0,b);
or a4(out,w1,w2);
endmodule


module mux_4x1(input s0,s1,a,b,c,d,output out);

wire inv_s0,inv_s1,w1,w2,w3,w4;

not a1(inv_s0,s0);
not a2(inv_s1,s1);

and a3(w1,s0,s1,a);
and a4(w2,inv_s0,s1,b);
and a5(w3,s0,inv_s1,c);
and a6(w4,inv_s0,inv_s1,d);

or a7(out,w1,w2,w3,w4);

endmodule


module mux8x1(input s0,s1,s2,a,b,c,d,e,f,g,h, output out);
wire w1,w2;

// mux_4x1 m1(s0,s1,e,f,g,h,w1);
// mux_4x1 m2(s0,s1,a,b,c,d,w2);
mux_4x1 m1(s0,s1,g,c,e,a,w1);
mux_4x1 m2(s0,s1,h,d,f,b,w2);

q2x1_MUX m3(s2,w1,w2,out);

endmodule

Assignment_1/1d/8x1_mux_tb.v
`timescale  1ns/10ps

module mux_tb;

reg s0,s1,s2,a,b,c,d,e,f,g,h;
wire out;

mux8x1 DUT(s0,s1,s2,a,b,c,d,e,f,g,h,out);


initial begin
    s0=1'b0;    
    s1=1'b0;    
    s2=1'b0;    
    a=1'b0;    
    b=1'b0;        
    c=1'b0;    
    d=1'b0;    
    e=1'b0;    
    f=1'b0;    
    g=1'b0;    
    h=1'b0;    
    #3200 $finish;
end

always #1600 s0= ~s0;
always #800 s1= ~s1;
always #400 s2= ~s2;
always #200 a= ~a;
always #100   b= ~b;
always #50 c= ~c;
always #25 d= ~d;
always #12.5 e= ~e;
always #6.25 f= ~f;
always #3.125 g= ~g;
always #1.5625 h= ~h;

initial begin
   	$monitor("%g Output=%b s0=%b s1=%b a=%b b=%b c=%b d=%b e=%b f=%b g=%b h=%b",$time,out,s0,s1,a,b,c,d,e,f,g,h);

    $dumpfile("q_2a.vcd");
    $dumpvars;
end
endmodule

Assignment_1/1d/q_2a.vcd
$date
	Fri Feb 18 12:19:03 2022
$end
$version
	Icarus Verilog
$end
$timescale
	10ps
$end
$scope module mux_tb $end
$var wire 1 ! out $end
$var reg 1 " a $end
$var reg 1 # b $end
$var reg 1 $ c $end
$var reg 1 % d $end
$var reg 1 & e $end
$var reg 1 ' f $end
$var reg 1 ( g $end
$var reg 1 ) h $end
$var reg 1 * s0 $end
$var reg 1 + s1 $end
$var reg 1 , s2 $end
$scope module DUT $end
$var wire 1 " a $end
$var wire 1 # b $end
$var wire 1 $ c $end
$var wire 1 % d $end
$var wire 1 & e $end
$var wire 1 ' f $end
$var wire 1 ( g $end
$var wire 1 ) h $end
$var wire 1 * s0 $end
$var wire 1 + s1 $end
$var wire 1 , s2 $end
$var wire 1 - w2 $end
$var wire 1 . w1 $end
$var wire 1 ! out $end
$scope module m1 $end
$var wire 1 ( a $end
$var wire 1 $ b $end
$var wire 1 & c $end
$var wire 1 " d $end
$var wire 1 / inv_s0 $end
$var wire 1 0 inv_s1 $end
$var wire 1 . out $end
$var wire 1 * s0 $end
$var wire 1 + s1 $end
$var wire 1 1 w1 $end
$var wire 1 2 w2 $end
$var wire 1 3 w3 $end
$var wire 1 4 w4 $end
$upscope $end
$scope module m2 $end
$var wire 1 ) a $end
$var wire 1 % b $end
$var wire 1 ' c $end
$var wire 1 # d $end
$var wire 1 5 inv_s0 $end
$var wire 1 6 inv_s1 $end
$var wire 1 - out $end
$var wire 1 * s0 $end
$var wire 1 + s1 $end
$var wire 1 7 w1 $end
$var wire 1 8 w2 $end
$var wire 1 9 w3 $end
$var wire 1 : w4 $end
$upscope $end
$scope module m3 $end
$var wire 1 . a $end
$var wire 1 - b $end
$var wire 1 ; inv_s0 $end
$var wire 1 ! out $end
$var wire 1 , s0 $end
$var wire 1 < w1 $end
$var wire 1 = w2 $end
$upscope $end
$upscope $end
$upscope $end
$enddefinitions $end
#0
$dumpvars
0=
0<
1;
0:
09
08
07
16
15
04
03
02
01
10
1/
0.
0-
0,
0+
0*
0)
0(
0'
0&
0%
0$
0#
0"
0!
$end
#156
1)
#312
0)
#313
1(
#468
1)
#624
0)
#625
1'
#626
0(
#780
1)
#936
0)
#939
1(
#1092
1)
#1248
0)
#1250
0'
1&
#1252
0(
#1404
1)
#1560
0)
#1565
1(
#1716
1)
#1872
0)
#1875
1'
#1878
0(
#2028
1)
#2184
0)
#2191
1(
#2340
1)
#2496
0)
#2500
0'
0&
1%
#2504
0(
#2652
1)
#2808
0)
#2817
1(
#2964
1)
#3120
0)
#3125
1'
#3130
0(
#3276
1)
#3432
0)
#3443
1(
#3588
1)
#3744
0)
#3750
0'
1&
#3756
0(
#3900
1)
#4056
0)
#4069
1(
#4212
1)
#4368
0)
#4375
1'
#4382
0(
#4524
1)
#4680
0)
#4695
1(
#4836
1)
#4992
0)
#5000
0'
0&
0%
1$
#5008
0(
#5148
1)
#5304
0)
#5321
1(
#5460
1)
#5616
0)
#5625
1'
#5634
0(
#5772
1)
#5928
0)
#5947
1(
#6084
1)
#6240
0)
#6250
0'
1&
#6260
0(
#6396
1)
#6552
0)
#6573
1(
#6708
1)
#6864
0)
#6875
1'
#6886
0(
#7020
1)
#7176
0)
#7199
1(
#7332
1)
#7488
0)
#7500
0'
0&
1%
#7512
0(
#7644
1)
#7800
0)
#7825
1(
#7956
1)
#8112
0)
#8125
1'
#8138
0(
#8268
1)
#8424
0)
#8451
1(
#8580
1)
#8736
0)
#8750
0'
1&
#8764
0(
#8892
1)
#9048
0)
#9077
1(
#9204
1)
#9360
0)
#9375
1'
#9390
0(
#9516
1)
#9672
0)
#9703
1(
#9828
1)
#9984
0)
#10000
1-
1:
0'
0&
0%
0$
1#
#10016
0(
#10140
1)
#10296
0)
#10329
1(
#10452
1)
#10608
0)
#10625
1'
#10642
0(
#10764
1)
#10920
0)
#10955
1(
#11076
1)
#11232
0)
#11250
0'
1&
#11268
0(
#11388
1)
#11544
0)
#11581
1(
#11700
1)
#11856
0)
#11875
1'
#11894
0(
#12012
1)
#12168
0)
#12207
1(
#12324
1)
#12480
0)
#12500
0'
0&
1%
#12520
0(
#12636
1)
#12792
0)
#12833
1(
#12948
1)
#13104
0)
#13125
1'
#13146
0(
#13260
1)
#13416
0)
#13459
1(
#13572
1)
#13728
0)
#13750
0'
1&
#13772
0(
#13884
1)
#14040
0)
#14085
1(
#14196
1)
#14352
0)
#14375
1'
#14398
0(
#14508
1)
#14664
0)
#14711
1(
#14820
1)
#14976
0)
#15000
0'
0&
0%
1$
#15024
0(
#15132
1)
#15288
0)
#15337
1(
#15444
1)
#15600
0)
#15625
1'
#15650
0(
#15756
1)
#15912
0)
#15963
1(
#16068
1)
#16224
0)
#16250
0'
1&
#16276
0(
#16380
1)
#16536
0)
#16589
1(
#16692
1)
#16848
0)
#16875
1'
#16902
0(
#17004
1)
#17160
0)
#17215
1(
#17316
1)
#17472
0)
#17500
0'
0&
1%
#17528
0(
#17628
1)
#17784
0)
#17841
1(
#17940
1)
#18096
0)
#18125
1'
#18154
0(
#18252
1)
#18408
0)
#18467
1(
#18564
1)
#18720
0)
#18750
0'
1&
#18780
0(
#18876
1)
#19032
0)
#19093
1(
#19188
1)
#19344
0)
#19375
1'
#19406
0(
#19500
1)
#19656
0)
#19719
1(
#19812
1)
#19968
0)
#20000
1!
1<
0-
1.
0:
14
0'
0&
0%
0$
0#
1"
#20032
0(
#20124
1)
#20280
0)
#20345
1(
#20436
1)
#20592
0)
#20625
1'
#20658
0(
#20748
1)
#20904
0)
#20971
1(
#21060
1)
#21216
0)
#21250
0'
1&
#21284
0(
#21372
1)
#21528
0)
#21597
1(
#21684
1)
#21840
0)
#21875
1'
#21910
0(
#21996
1)
#22152
0)
#22223
1(
#22308
1)
#22464
0)
#22500
0'
0&
1%
#22536
0(
#22620
1)
#22776
0)
#22849
1(
#22932
1)
#23088
0)
#23125
1'
#23162
0(
#23244
1)
#23400
0)
#23475
1(
#23556
1)
#23712
0)
#23750
0'
1&
#23788
0(
#23868
1)
#24024
0)
#24101
1(
#24180
1)
#24336
0)
#24375
1'
#24414
0(
#24492
1)
#24648
0)
#24727
1(
#24804
1)
#24960
0)
#25000
0'
0&
0%
1$
#25040
0(
#25116
1)
#25272
0)
#25353
1(
#25428
1)
#25584
0)
#25625
1'
#25666
0(
#25740
1)
#25896
0)
#25979
1(
#26052
1)
#26208
0)
#26250
0'
1&
#26292
0(
#26364
1)
#26520
0)
#26605
1(
#26676
1)
#26832
0)
#26875
1'
#26918
0(
#26988
1)
#27144
0)
#27231
1(
#27300
1)
#27456
0)
#27500
0'
0&
1%
#27544
0(
#27612
1)
#27768
0)
#27857
1(
#27924
1)
#28080
0)
#28125
1'
#28170
0(
#28236
1)
#28392
0)
#28483
1(
#28548
1)
#28704
0)
#28750
0'
1&
#28796
0(
#28860
1)
#29016
0)
#29109
1(
#29172
1)
#29328
0)
#29375
1'
#29422
0(
#29484
1)
#29640
0)
#29735
1(
#29796
1)
#29952
0)
#30000
1-
1:
0'
0&
0%
0$
1#
#30048
0(
#30108
1)
#30264
0)
#30361
1(
#30420
1)
#30576
0)
#30625
1'
#30674
0(
#30732
1)
#30888
0)
#30987
1(
#31044
1)
#31200
0)
#31250
0'
1&
#31300
0(
#31356
1)
#31512
0)
#31613
1(
#31668
1)
#31824
0)
#31875
1'
#31926
0(
#31980
1)
#32136
0)
#32239
1(
#32292
1)
#32448
0)
#32500
0'
0&
1%
#32552
0(
#32604
1)
#32760
0)
#32865
1(
#32916
1)
#33072
0)
#33125
1'
#33178
0(
#33228
1)
#33384
0)
#33491
1(
#33540
1)
#33696
0)
#33750
0'
1&
#33804
0(
#33852
1)
#34008
0)
#34117
1(
#34164
1)
#34320
0)
#34375
1'
#34430
0(
#34476
1)
#34632
0)
#34743
1(
#34788
1)
#34944
0)
#35000
0'
0&
0%
1$
#35056
0(
#35100
1)
#35256
0)
#35369
1(
#35412
1)
#35568
0)
#35625
1'
#35682
0(
#35724
1)
#35880
0)
#35995
1(
#36036
1)
#36192
0)
#36250
0'
1&
#36308
0(
#36348
1)
#36504
0)
#36621
1(
#36660
1)
#36816
0)
#36875
1'
#36934
0(
#36972
1)
#37128
0)
#37247
1(
#37284
1)
#37440
0)
#37500
0'
0&
1%
#37560
0(
#37596
1)
#37752
0)
#37873
1(
#37908
1)
#38064
0)
#38125
1'
#38186
0(
#38220
1)
#38376
0)
#38499
1(
#38532
1)
#38688
0)
#38750
0'
1&
#38812
0(
#38844
1)
#39000
0)
#39125
1(
#39156
1)
#39312
0)
#39375
1'
#39438
0(
#39468
1)
#39624
0)
#39751
1(
#39780
1)
#39936
0)
#40000
0!
0-
0.
0<
0:
04
0;
0=
0'
0&
0%
0$
0#
0"
1,
#40064
0(
#40092
1)
#40248
0)
#40377
1(
#40404
1)
#40560
0)
#40625
1'
#40690
0(
#40716
1)
#40872
0)
#41003
1(
#41028
1)
#41184
0)
#41250
0'
1&
#41316
0(
#41340
1)
#41496
0)
#41629
1(
#41652
1)
#41808
0)
#41875
1'
#41942
0(
#41964
1)
#42120
0)
#42255
1(
#42276
1)
#42432
0)
#42500
0'
0&
1%
#42568
0(
#42588
1)
#42744
0)
#42881
1(
#42900
1)
#43056
0)
#43125
1'
#43194
0(
#43212
1)
#43368
0)
#43507
1(
#43524
1)
#43680
0)
#43750
0'
1&
#43820
0(
#43836
1)
#43992
0)
#44133
1(
#44148
1)
#44304
0)
#44375
1'
#44446
0(
#44460
1)
#44616
0)
#44759
1(
#44772
1)
#44928
0)
#45000
0'
0&
0%
1$
#45072
0(
#45084
1)
#45240
0)
#45385
1(
#45396
1)
#45552
0)
#45625
1'
#45698
0(
#45708
1)
#45864
0)
#46011
1(
#46020
1)
#46176
0)
#46250
0'
1&
#46324
0(
#46332
1)
#46488
0)
#46637
1(
#46644
1)
#46800
0)
#46875
1'
#46950
0(
#46956
1)
#47112
0)
#47263
1(
#47268
1)
#47424
0)
#47500
0'
0&
1%
#47576
0(
#47580
1)
#47736
0)
#47889
1(
#47892
1)
#48048
0)
#48125
1'
#48202
0(
#48204
1)
#48360
0)
#48515
1(
#48516
1)
#48672
0)
#48750
0'
1&
#48828
1)
0(
#48984
0)
#49140
1)
#49141
1(
#49296
0)
#49375
1'
#49452
1)
#49454
0(
#49608
0)
#49764
1)
#49767
1(
#49920
0)
#50000
1!
1=
1-
1:
0'
0&
0%
0$
1#
#50076
1)
#50080
0(
#50232
0)
#50388
1)
#50393
1(
#50544
0)
#50625
1'
#50700
1)
#50706
0(
#50856
0)
#51012
1)
#51019
1(
#51168
0)
#51250
0'
1&
#51324
1)
#51332
0(
#51480
0)
#51636
1)
#51645
1(
#51792
0)
#51875
1'
#51948
1)
#51958
0(
#52104
0)
#52260
1)
#52271
1(
#52416
0)
#52500
0'
0&
1%
#52572
1)
#52584
0(
#52728
0)
#52884
1)
#52897
1(
#53040
0)
#53125
1'
#53196
1)
#53210
0(
#53352
0)
#53508
1)
#53523
1(
#53664
0)
#53750
0'
1&
#53820
1)
#53836
0(
#53976
0)
#54132
1)
#54149
1(
#54288
0)
#54375
1'
#54444
1)
#54462
0(
#54600
0)
#54756
1)
#54775
1(
#54912
0)
#55000
0'
0&
0%
1$
#55068
1)
#55088
0(
#55224
0)
#55380
1)
#55401
1(
#55536
0)
#55625
1'
#55692
1)
#55714
0(
#55848
0)
#56004
1)
#56027
1(
#56160
0)
#56250
0'
1&
#56316
1)
#56340
0(
#56472
0)
#56628
1)
#56653
1(
#56784
0)
#56875
1'
#56940
1)
#56966
0(
#57096
0)
#57252
1)
#57279
1(
#57408
0)
#57500
0'
0&
1%
#57564
1)
#57592
0(
#57720
0)
#57876
1)
#57905
1(
#58032
0)
#58125
1'
#58188
1)
#58218
0(
#58344
0)
#58500
1)
#58531
1(
#58656
0)
#58750
0'
1&
#58812
1)
#58844
0(
#58968
0)
#59124
1)
#59157
1(
#59280
0)
#59375
1'
#59436
1)
#59470
0(
#59592
0)
#59748
1)
#59783
1(
#59904
0)
#60000
0!
0=
0-
1.
0:
14
0'
0&
0%
0$
0#
1"
#60060
1)
#60096
0(
#60216
0)
#60372
1)
#60409
1(
#60528
0)
#60625
1'
#60684
1)
#60722
0(
#60840
0)
#60996
1)
#61035
1(
#61152
0)
#61250
0'
1&
#61308
1)
#61348
0(
#61464
0)
#61620
1)
#61661
1(
#61776
0)
#61875
1'
#61932
1)
#61974
0(
#62088
0)
#62244
1)
#62287
1(
#62400
0)
#62500
0'
0&
1%
#62556
1)
#62600
0(
#62712
0)
#62868
1)
#62913
1(
#63024
0)
#63125
1'
#63180
1)
#63226
0(
#63336
0)
#63492
1)
#63539
1(
#63648
0)
#63750
0'
1&
#63804
1)
#63852
0(
#63960
0)
#64116
1)
#64165
1(
#64272
0)
#64375
1'
#64428
1)
#64478
0(
#64584
0)
#64740
1)
#64791
1(
#64896
0)
#65000
0'
0&
0%
1$
#65052
1)
#65104
0(
#65208
0)
#65364
1)
#65417
1(
#65520
0)
#65625
1'
#65676
1)
#65730
0(
#65832
0)
#65988
1)
#66043
1(
#66144
0)
#66250
0'
1&
#66300
1)
#66356
0(
#66456
0)
#66612
1)
#66669
1(
#66768
0)
#66875
1'
#66924
1)
#66982
0(
#67080
0)
#67236
1)
#67295
1(
#67392
0)
#67500
0'
0&
1%
#67548
1)
#67608
0(
#67704
0)
#67860
1)
#67921
1(
#68016
0)
#68125
1'
#68172
1)
#68234
0(
#68328
0)
#68484
1)
#68547
1(
#68640
0)
#68750
0'
1&
#68796
1)
#68860
0(
#68952
0)
#69108
1)
#69173
1(
#69264
0)
#69375
1'
#69420
1)
#69486
0(
#69576
0)
#69732
1)
#69799
1(
#69888
0)
#70000
1!
1=
1-
1:
0'
0&
0%
0$
1#
#70044
1)
#70112
0(
#70200
0)
#70356
1)
#70425
1(
#70512
0)
#70625
1'
#70668
1)
#70738
0(
#70824
0)
#70980
1)
#71051
1(
#71136
0)
#71250
0'
1&
#71292
1)
#71364
0(
#71448
0)
#71604
1)
#71677
1(
#71760
0)
#71875
1'
#71916
1)
#71990
0(
#72072
0)
#72228
1)
#72303
1(
#72384
0)
#72500
0'
0&
1%
#72540
1)
#72616
0(
#72696
0)
#72852
1)
#72929
1(
#73008
0)
#73125
1'
#73164
1)
#73242
0(
#73320
0)
#73476
1)
#73555
1(
#73632
0)
#73750
0'
1&
#73788
1)
#73868
0(
#73944
0)
#74100
1)
#74181
1(
#74256
0)
#74375
1'
#74412
1)
#74494
0(
#74568
0)
#74724
1)
#74807
1(
#74880
0)
#75000
0'
0&
0%
1$
#75036
1)
#75120
0(
#75192
0)
#75348
1)
#75433
1(
#75504
0)
#75625
1'
#75660
1)
#75746
0(
#75816
0)
#75972
1)
#76059
1(
#76128
0)
#76250
0'
1&
#76284
1)
#76372
0(
#76440
0)
#76596
1)
#76685
1(
#76752
0)
#76875
1'
#76908
1)
#76998
0(
#77064
0)
#77220
1)
#77311
1(
#77376
0)
#77500
0'
0&
1%
#77532
1)
#77624
0(
#77688
0)
#77844
1)
#77937
1(
#78000
0)
#78125
1'
#78156
1)
#78250
0(
#78312
0)
#78468
1)
#78563
1(
#78624
0)
#78750
0'
1&
#78780
1)
#78876
0(
#78936
0)
#79092
1)
#79189
1(
#79248
0)
#79375
1'
#79404
1)
#79502
0(
#79560
0)
#79716
1)
#79815
1(
#79872
0)
#80000
0-
0.
0<
0!
0:
04
1;
0=
00
06
0'
0&
0%
0$
0#
0"
0,
1+
#80028
1)
#80128
0(
#80184
0)
#80340
1)
#80441
1(
#80496
0)
#80625
1'
#80652
1)
#80754
0(
#80808
0)
#80964
1)
#81067
1(
#81120
0)
#81250
0'
1&
#81276
1)
#81380
0(
#81432
0)
#81588
1)
#81693
1(
#81744
0)
#81875
1'
#81900
1)
#82006
0(
#82056
0)
#82212
1)
#82319
1(
#82368
0)
#82500
1-
18
0'
0&
1%
#82524
1)
#82632
0(
#82680
0)
#82836
1)
#82945
1(
#82992
0)
#83125
1'
#83148
1)
#83258
0(
#83304
0)
#83460
1)
#83571
1(
#83616
0)
#83750
0'
1&
#83772
1)
#83884
0(
#83928
0)
#84084
1)
#84197
1(
#84240
0)
#84375
1'
#84396
1)
#84510
0(
#84552
0)
#84708
1)
#84823
1(
#84864
0)
#85000
1!
1<
0-
1.
08
12
0'
0&
0%
1$
#85020
1)
#85136
0(
#85176
0)
#85332
1)
#85449
1(
#85488
0)
#85625
1'
#85644
1)
#85762
0(
#85800
0)
#85956
1)
#86075
1(
#86112
0)
#86250
0'
1&
#86268
1)
#86388
0(
#86424
0)
#86580
1)
#86701
1(
#86736
0)
#86875
1'
#86892
1)
#87014
0(
#87048
0)
#87204
1)
#87327
1(
#87360
0)
#87500
1-
18
0'
0&
1%
#87516
1)
#87640
0(
#87672
0)
#87828
1)
#87953
1(
#87984
0)
#88125
1'
#88140
1)
#88266
0(
#88296
0)
#88452
1)
#88579
1(
#88608
0)
#88750
0'
1&
#88764
1)
#88892
0(
#88920
0)
#89076
1)
#89205
1(
#89232
0)
#89375
1'
#89388
1)
#89518
0(
#89544
0)
#89700
1)
#89831
1(
#89856
0)
#90000
0!
0<
0-
0.
08
02
0'
0&
0%
0$
1#
#90012
1)
#90144
0(
#90168
0)
#90324
1)
#90457
1(
#90480
0)
#90625
1'
#90636
1)
#90770
0(
#90792
0)
#90948
1)
#91083
1(
#91104
0)
#91250
0'
1&
#91260
1)
#91396
0(
#91416
0)
#91572
1)
#91709
1(
#91728
0)
#91875
1'
#91884
1)
#92022
0(
#92040
0)
#92196
1)
#92335
1(
#92352
0)
#92500
1-
18
0'
0&
1%
#92508
1)
#92648
0(
#92664
0)
#92820
1)
#92961
1(
#92976
0)
#93125
1'
#93132
1)
#93274
0(
#93288
0)
#93444
1)
#93587
1(
#93600
0)
#93750
0'
1&
#93756
1)
#93900
0(
#93912
0)
#94068
1)
#94213
1(
#94224
0)
#94375
1'
#94380
1)
#94526
0(
#94536
0)
#94692
1)
#94839
1(
#94848
0)
#95000
1!
1<
0-
1.
08
12
0'
0&
0%
1$
#95004
1)
#95152
0(
#95160
0)
#95316
1)
#95465
1(
#95472
0)
#95625
1'
#95628
1)
#95778
0(
#95784
0)
#95940
1)
#96091
1(
#96096
0)
#96250
0'
1&
#96252
1)
#96404
0(
#96408
0)
#96564
1)
#96717
1(
#96720
0)
#96875
1'
#96876
1)
#97030
0(
#97032
0)
#97188
1)
#97343
1(
#97344
0)
#97500
1-
18
1)
0'
0&
1%
#97656
0)
0(
#97812
1)
#97968
0)
#97969
1(
#98124
1)
#98125
1'
#98280
0)
#98282
0(
#98436
1)
#98592
0)
#98595
1(
#98748
1)
#98750
0'
1&
#98904
0)
#98908
0(
#99060
1)
#99216
0)
#99221
1(
#99372
1)
#99375
1'
#99528
0)
#99534
0(
#99684
1)
#99840
0)
#99847
1(
#99996
1)
#100000
0!
0<
0-
0.
08
02
0'
0&
0%
0$
0#
1"
#100152
0)
#100160
0(
#100308
1)
#100464
0)
#100473
1(
#100620
1)
#100625
1'
#100776
0)
#100786
0(
#100932
1)
#101088
0)
#101099
1(
#101244
1)
#101250
0'
1&
#101400
0)
#101412
0(
#101556
1)
#101712
0)
#101725
1(
#101868
1)
#101875
1'
#102024
0)
#102038
0(
#102180
1)
#102336
0)
#102351
1(
#102492
1)
#102500
1-
18
0'
0&
1%
#102648
0)
#102664
0(
#102804
1)
#102960
0)
#102977
1(
#103116
1)
#103125
1'
#103272
0)
#103290
0(
#103428
1)
#103584
0)
#103603
1(
#103740
1)
#103750
0'
1&
#103896
0)
#103916
0(
#104052
1)
#104208
0)
#104229
1(
#104364
1)
#104375
1'
#104520
0)
#104542
0(
#104676
1)
#104832
0)
#104855
1(
#104988
1)
#105000
1!
1<
0-
1.
08
12
0'
0&
0%
1$
#105144
0)
#105168
0(
#105300
1)
#105456
0)
#105481
1(
#105612
1)
#105625
1'
#105768
0)
#105794
0(
#105924
1)
#106080
0)
#106107
1(
#106236
1)
#106250
0'
1&
#106392
0)
#106420
0(
#106548
1)
#106704
0)
#106733
1(
#106860
1)
#106875
1'
#107016
0)
#107046
0(
#107172
1)
#107328
0)
#107359
1(
#107484
1)
#107500
1-
18
0'
0&
1%
#107640
0)
#107672
0(
#107796
1)
#107952
0)
#107985
1(
#108108
1)
#108125
1'
#108264
0)
#108298
0(
#108420
1)
#108576
0)
#108611
1(
#108732
1)
#108750
0'
1&
#108888
0)
#108924
0(
#109044
1)
#109200
0)
#109237
1(
#109356
1)
#109375
1'
#109512
0)
#109550
0(
#109668
1)
#109824
0)
#109863
1(
#109980
1)
#110000
0!
0<
0-
0.
08
02
0'
0&
0%
0$
1#
#110136
0)
#110176
0(
#110292
1)
#110448
0)
#110489
1(
#110604
1)
#110625
1'
#110760
0)
#110802
0(
#110916
1)
#111072
0)
#111115
1(
#111228
1)
#111250
0'
1&
#111384
0)
#111428
0(
#111540
1)
#111696
0)
#111741
1(
#111852
1)
#111875
1'
#112008
0)
#112054
0(
#112164
1)
#112320
0)
#112367
1(
#112476
1)
#112500
1-
18
0'
0&
1%
#112632
0)
#112680
0(
#112788
1)
#112944
0)
#112993
1(
#113100
1)
#113125
1'
#113256
0)
#113306
0(
#113412
1)
#113568
0)
#113619
1(
#113724
1)
#113750
0'
1&
#113880
0)
#113932
0(
#114036
1)
#114192
0)
#114245
1(
#114348
1)
#114375
1'
#114504
0)
#114558
0(
#114660
1)
#114816
0)
#114871
1(
#114972
1)
#115000
1!
1<
0-
1.
08
12
0'
0&
0%
1$
#115128
0)
#115184
0(
#115284
1)
#115440
0)
#115497
1(
#115596
1)
#115625
1'
#115752
0)
#115810
0(
#115908
1)
#116064
0)
#116123
1(
#116220
1)
#116250
0'
1&
#116376
0)
#116436
0(
#116532
1)
#116688
0)
#116749
1(
#116844
1)
#116875
1'
#117000
0)
#117062
0(
#117156
1)
#117312
0)
#117375
1(
#117468
1)
#117500
1-
18
0'
0&
1%
#117624
0)
#117688
0(
#117780
1)
#117936
0)
#118001
1(
#118092
1)
#118125
1'
#118248
0)
#118314
0(
#118404
1)
#118560
0)
#118627
1(
#118716
1)
#118750
0'
1&
#118872
0)
#118940
0(
#119028
1)
#119184
0)
#119253
1(
#119340
1)
#119375
1'
#119496
0)
#119566
0(
#119652
1)
#119808
0)
#119879
1(
#119964
1)
#120000
0!
0-
0.
0<
08
02
0;
0=
0'
0&
0%
0$
0#
0"
1,
#120120
0)
#120192
0(
#120276
1)
#120432
0)
#120505
1(
#120588
1)
#120625
1'
#120744
0)
#120818
0(
#120900
1)
#121056
0)
#121131
1(
#121212
1)
#121250
0'
1&
#121368
0)
#121444
0(
#121524
1)
#121680
0)
#121757
1(
#121836
1)
#121875
1'
#121992
0)
#122070
0(
#122148
1)
#122304
0)
#122383
1(
#122460
1)
#122500
1!
1=
1-
18
0'
0&
1%
#122616
0)
#122696
0(
#122772
1)
#122928
0)
#123009
1(
#123084
1)
#123125
1'
#123240
0)
#123322
0(
#123396
1)
#123552
0)
#123635
1(
#123708
1)
#123750
0'
1&
#123864
0)
#123948
0(
#124020
1)
#124176
0)
#124261
1(
#124332
1)
#124375
1'
#124488
0)
#124574
0(
#124644
1)
#124800
0)
#124887
1(
#124956
1)
#125000
0!
0=
0-
1.
08
12
0'
0&
0%
1$
#125112
0)
#125200
0(
#125268
1)
#125424
0)
#125513
1(
#125580
1)
#125625
1'
#125736
0)
#125826
0(
#125892
1)
#126048
0)
#126139
1(
#126204
1)
#126250
0'
1&
#126360
0)
#126452
0(
#126516
1)
#126672
0)
#126765
1(
#126828
1)
#126875
1'
#126984
0)
#127078
0(
#127140
1)
#127296
0)
#127391
1(
#127452
1)
#127500
1!
1=
1-
18
0'
0&
1%
#127608
0)
#127704
0(
#127764
1)
#127920
0)
#128017
1(
#128076
1)
#128125
1'
#128232
0)
#128330
0(
#128388
1)
#128544
0)
#128643
1(
#128700
1)
#128750
0'
1&
#128856
0)
#128956
0(
#129012
1)
#129168
0)
#129269
1(
#129324
1)
#129375
1'
#129480
0)
#129582
0(
#129636
1)
#129792
0)
#129895
1(
#129948
1)
#130000
0!
0=
0-
0.
08
02
0'
0&
0%
0$
1#
#130104
0)
#130208
0(
#130260
1)
#130416
0)
#130521
1(
#130572
1)
#130625
1'
#130728
0)
#130834
0(
#130884
1)
#131040
0)
#131147
1(
#131196
1)
#131250
0'
1&
#131352
0)
#131460
0(
#131508
1)
#131664
0)
#131773
1(
#131820
1)
#131875
1'
#131976
0)
#132086
0(
#132132
1)
#132288
0)
#132399
1(
#132444
1)
#132500
1!
1=
1-
18
0'
0&
1%
#132600
0)
#132712
0(
#132756
1)
#132912
0)
#133025
1(
#133068
1)
#133125
1'
#133224
0)
#133338
0(
#133380
1)
#133536
0)
#133651
1(
#133692
1)
#133750
0'
1&
#133848
0)
#133964
0(
#134004
1)
#134160
0)
#134277
1(
#134316
1)
#134375
1'
#134472
0)
#134590
0(
#134628
1)
#134784
0)
#134903
1(
#134940
1)
#135000
0!
0=
0-
1.
08
12
0'
0&
0%
1$
#135096
0)
#135216
0(
#135252
1)
#135408
0)
#135529
1(
#135564
1)
#135625
1'
#135720
0)
#135842
0(
#135876
1)
#136032
0)
#136155
1(
#136188
1)
#136250
0'
1&
#136344
0)
#136468
0(
#136500
1)
#136656
0)
#136781
1(
#136812
1)
#136875
1'
#136968
0)
#137094
0(
#137124
1)
#137280
0)
#137407
1(
#137436
1)
#137500
1!
1=
1-
18
0'
0&
1%
#137592
0)
#137720
0(
#137748
1)
#137904
0)
#138033
1(
#138060
1)
#138125
1'
#138216
0)
#138346
0(
#138372
1)
#138528
0)
#138659
1(
#138684
1)
#138750
0'
1&
#138840
0)
#138972
0(
#138996
1)
#139152
0)
#139285
1(
#139308
1)
#139375
1'
#139464
0)
#139598
0(
#139620
1)
#139776
0)
#139911
1(
#139932
1)
#140000
0!
0=
0-
0.
08
02
0'
0&
0%
0$
0#
1"
#140088
0)
#140224
0(
#140244
1)
#140400
0)
#140537
1(
#140556
1)
#140625
1'
#140712
0)
#140850
0(
#140868
1)
#141024
0)
#141163
1(
#141180
1)
#141250
0'
1&
#141336
0)
#141476
0(
#141492
1)
#141648
0)
#141789
1(
#141804
1)
#141875
1'
#141960
0)
#142102
0(
#142116
1)
#142272
0)
#142415
1(
#142428
1)
#142500
1!
1=
1-
18
0'
0&
1%
#142584
0)
#142728
0(
#142740
1)
#142896
0)
#143041
1(
#143052
1)
#143125
1'
#143208
0)
#143354
0(
#143364
1)
#143520
0)
#143667
1(
#143676
1)
#143750
0'
1&
#143832
0)
#143980
0(
#143988
1)
#144144
0)
#144293
1(
#144300
1)
#144375
1'
#144456
0)
#144606
0(
#144612
1)
#144768
0)
#144919
1(
#144924
1)
#145000
0!
0=
0-
1.
08
12
0'
0&
0%
1$
#145080
0)
#145232
0(
#145236
1)
#145392
0)
#145545
1(
#145548
1)
#145625
1'
#145704
0)
#145858
0(
#145860
1)
#146016
0)
#146171
1(
#146172
1)
#146250
0'
1&
#146328
0)
#146484
1)
0(
#146640
0)
#146796
1)
#146797
1(
#146875
1'
#146952
0)
#147108
1)
#147110
0(
#147264
0)
#147420
1)
#147423
1(
#147500
1!
1=
1-
18
0'
0&
1%
#147576
0)
#147732
1)
#147736
0(
#147888
0)
#148044
1)
#148049
1(
#148125
1'
#148200
0)
#148356
1)
#148362
0(
#148512
0)
#148668
1)
#148675
1(
#148750
0'
1&
#148824
0)
#148980
1)
#148988
0(
#149136
0)
#149292
1)
#149301
1(
#149375
1'
#149448
0)
#149604
1)
#149614
0(
#149760
0)
#149916
1)
#149927
1(
#150000
0!
0=
0-
0.
08
02
0'
0&
0%
0$
1#
#150072
0)
#150228
1)
#150240
0(
#150384
0)
#150540
1)
#150553
1(
