Assignment_1/1b/4x1mux.v
module mux_4x1(input s0,s1,a,b,c,d,output out);

wire inv_s0,inv_s1,w1,w2,w3,w4;

not a1(inv_s0,s0);
not a2(inv_s1,s1);

and a3(w1,s0,s1,a);
and a4(w2,inv_s0,s1,b);
and a5(w3,s0,inv_s1,c);
and a6(w4,inv_s0,inv_s1,d);

or a7(out,w1,w2,w3,w4);

endmodule

Assignment_1/1c/4x1_mux_tb.v
`timescale  1ns/10ps

module mux_tb;

reg s0,s1,a,b,c,d;
wire out;

mux_4x1 DUT(s0,s1,a,b,c,d,out);


initial begin
    s0=1'b0;    
    s1=1'b0;    
    a=1'b0;    
    b=1'b0;        
    c=1'b0;    
    d=1'b0;    
    #500 $finish;
end

always #400 s0= ~s0;
always #200 s1= ~s1;
always #100 a= ~a;
always #50   b= ~b;
always #25 c= ~c;
always #12.5 d= ~d;

initial begin
   	$monitor("%g Output=%b s0=%b s1=%b a=%b b=%b c=%b d=%b",$time,out,s0,s1,a,b,c,d);

    $dumpfile("q_2a.vcd");
    $dumpvars;
end
endmodule

Assignment_1/1b/q_2a.vcd
$date
	Fri Feb 18 03:51:54 2022
$end
$version
	Icarus Verilog
$end
$timescale
	10ps
$end
$scope module mux_tb $end
$var wire 1 ! out $end
$var reg 1 " a $end
$var reg 1 # b $end
$var reg 1 $ c $end
$var reg 1 % d $end
$var reg 1 & s0 $end
$var reg 1 ' s1 $end
$scope module DUT $end
$var wire 1 " a $end
$var wire 1 # b $end
$var wire 1 $ c $end
$var wire 1 % d $end
$var wire 1 ( inv_s0 $end
$var wire 1 ) inv_s1 $end
$var wire 1 ! out $end
$var wire 1 & s0 $end
$var wire 1 ' s1 $end
$var wire 1 * w1 $end
$var wire 1 + w2 $end
$var wire 1 , w3 $end
$var wire 1 - w4 $end
$upscope $end
$upscope $end
$enddefinitions $end
#0
$dumpvars
0-
0,
0+
0*
1)
1(
0'
0&
0%
0$
0#
0"
0!
$end
#1250
1!
1-
1%
#2500
0!
0-
0%
1$
#3750
1!
1-
1%
#5000
0!
0-
0%
0$
1#
#6250
1!
1-
1%
#7500
0!
0-
0%
1$
#8750
1!
1-
1%
#10000
0!
0-
0%
0$
0#
1"
#11250
1!
1-
1%
#12500
0!
0-
0%
1$
#13750
1!
1-
1%
#15000
0!
0-
0%
0$
1#
#16250
1!
1-
1%
#17500
0!
0-
0%
1$
#18750
1!
1-
1%
#20000
0!
0-
0)
0%
0$
0#
0"
1'
#21250
1%
#22500
0%
1$
#23750
1%
#25000
1!
1+
0%
0$
1#
#26250
1%
#27500
0%
1$
#28750
1%
#30000
0!
0+
0%
0$
0#
1"
#31250
1%
#32500
0%
1$
#33750
1%
#35000
1!
1+
0%
0$
1#
#36250
1%
#37500
0%
1$
#38750
1%
#40000
0!
1)
0+
0(
0%
0$
0#
0"
0'
1&
#41250
1%
#42500
1!
1,
0%
1$
#43750
1%
#45000
0!
0,
0%
0$
1#
#46250
1%
#47500
1!
1,
0%
1$
#48750
1%
#50000
0!
0,
0%
0$
0#
1"
